imgc/__init__.py
imgc/wrap.py
imgc-0.1.0.dist-info/DESCRIPTION.rst
imgc-0.1.0.dist-info/METADATA
imgc-0.1.0.dist-info/RECORD
imgc-0.1.0.dist-info/WHEEL
imgc-0.1.0.dist-info/entry_points.txt
imgc-0.1.0.dist-info/metadata.json
imgc-0.1.0.dist-info/top_level.txt
